mcp_pr_recommender/__init__.py
mcp_pr_recommender/cli.py
mcp_pr_recommender/config.py
mcp_pr_recommender/main.py
mcp_pr_recommender/models/pr/recommendations.py
mcp_pr_recommender/prompts.py
mcp_pr_recommender/services/__init__.py
mcp_pr_recommender/services/atomicity_validator.py
mcp_pr_recommender/services/grouping_engine.py
mcp_pr_recommender/services/semantic_analyzer.py
mcp_pr_recommender/tools/__init__.py
mcp_pr_recommender/tools/feasibility_analyzer_tool.py
mcp_pr_recommender/tools/pr_recommender_tool.py
mcp_pr_recommender/tools/strategy_manager_tool.py
mcp_pr_recommender/tools/validator_tool.py
mcp_shared_lib/__init__.py
mcp_shared_lib/config/__init__.py
mcp_shared_lib/config/base.py
mcp_shared_lib/config/git_analyzer.py
mcp_shared_lib/models/__init__.py
mcp_shared_lib/models/analysis/__init__.py
mcp_shared_lib/models/analysis/categorization.py
mcp_shared_lib/models/analysis/repository.py
mcp_shared_lib/models/analysis/results.py
mcp_shared_lib/models/analysis/risk.py
mcp_shared_lib/models/base/common.py
mcp_shared_lib/models/base/types.py
mcp_shared_lib/models/git/changes.py
mcp_shared_lib/models/git/commits.py
mcp_shared_lib/models/git/files.py
mcp_shared_lib/models/git/repository.py
mcp_shared_lib/py.typed
mcp_shared_lib/server/__init__.py
mcp_shared_lib/server/runner.py
mcp_shared_lib/services/__init__.py
mcp_shared_lib/services/git/git_client.py
mcp_shared_lib/test_utils/__init__.py
mcp_shared_lib/test_utils/factories/__init__.py
mcp_shared_lib/test_utils/factories/analysis.py
mcp_shared_lib/test_utils/factories/base.py
mcp_shared_lib/test_utils/factories/files.py
mcp_shared_lib/test_utils/factories/git.py
mcp_shared_lib/test_utils/factories/recommendations.py
mcp_shared_lib/test_utils/factories/scenarios.py
mcp_shared_lib/test_utils/factories/tools.py
mcp_shared_lib/tools/__init__.py
mcp_shared_lib/tools/base.py
mcp_shared_lib/transports/__init__.py
mcp_shared_lib/transports/base.py
mcp_shared_lib/transports/config.py
mcp_pr_recommender-0.1.0.dist-info/METADATA
mcp_pr_recommender-0.1.0.dist-info/WHEEL
mcp_pr_recommender-0.1.0.dist-info/entry_points.txt
mcp_pr_recommender-0.1.0.dist-info/RECORD
